tgzr/shell_hosts/blender/__init__.py
tgzr/shell_hosts/blender/_version.py
tgzr/shell_hosts/blender/app.py
tgzr/shell_hosts/blender/run_blender.py
tgzr_shell_hosts_blender-0.100.dist-info/METADATA
tgzr_shell_hosts_blender-0.100.dist-info/WHEEL
tgzr_shell_hosts_blender-0.100.dist-info/entry_points.txt
tgzr_shell_hosts_blender-0.100.dist-info/licenses/LICENSE
tgzr_shell_hosts_blender-0.100.dist-info/RECORD
